{
  "id": "eafebea2-cdc4-4c1b-b151-0d7c7b7c2493",
  "timestamp": 1618386940.141,
  "keyword": [
    "title:FOSS",
    "FOSS",
    "Stallman",
    "RMS",
    "toxic culture",
    "FSF",
    "misogyny"
  ],
  "extra": [],
  "note": "Michael Meeks talks about RMS, specifically referencing potentially warning women of RMS (2019). Michael Meeks also talks about RMS not enganging well with the criticisms against him.",
  "link": [
    "https://people.gnome.org/~michael/blog/2019-09-17-rms.html",
    "https://web.archive.org/web/20191226085022/https://people.gnome.org/~michael/blog/2019-09-17-rms.html",
    "https://people.gnome.org/~michael/blog/2021-03-22.html",
    "https://web.archive.org/web/20210406184622/https://people.gnome.org/~michael/blog/2021-03-22.html",
    "https://people.gnome.org/~michael/blog/2021-04-12-excommunicating.html",
    "https://web.archive.org/web/20210414072528/https://people.gnome.org/~michael/blog/2021-04-12-excommunicating.html"
  ]
}